__init__.py
calc.py
const.py
hoja19-1.py
hoja19-2.py
hoja19-3.py
hoja19-4.py
libro.py
triangulo4.py
triangulo5.py
ejertri_calc-0.0.4.dist-info/METADATA
ejertri_calc-0.0.4.dist-info/WHEEL
ejertri_calc-0.0.4.dist-info/licenses/LICENSE
ejertri_calc-0.0.4.dist-info/RECORD
