Metadata-Version: 2.1
Name: ejertri-calc
Version: 0.0.4
Summary: Ejemplo de como crear un paquete
Project-URL: Homepage, https://github.com/ertetejose/.gitignore.git
Project-URL: Bug Tracker, https://github.com/ertetejose/.gitignore.git/issues
Author-email: ertetejose <josemaxdd@gmail.com>
License-File: LICENSE
Classifier: License :: OSI Approved :: MIT License
Classifier: Operating System :: OS Independent
Classifier: Programming Language :: Python :: 3
Requires-Python: >=3.3
